[
  {
    "id": "01",
    "url": "https://digdeeper.love/",
    "img": "/static/buttons/digdeeperbutton.png",
    "name": "DigDeeper",
    "desc": "Este sitio es para el paranoico como un profeta para el cristiano."
  },
  {
    "id": "02",
    "url": "https://getgle.org",
    "img": "/static/buttons/getgle.gif",
    "name": "Getgle",
    "desc": "Una cloaca de degenerados adictos al Futanari y fanáticos de Jeffrey Epstein. (Solo quiero ser uno de ellos, quiero sentarme con ellos...)"
  },
  {
    "id": "03",
    "url": "https://eldeadkennedy.neocities.org/",
    "img": "/static/buttons/deadkennedy.gif",
    "name": "La Virgocueva de DeadKennedy",
    "desc": "El YouTuber chistoso con un trapo sucio en la cabeza."
  },
  {
    "id": "04",
    "url": "https://lukesmith.xyz/",
    "img": "/static/buttons/lukesmith.gif",
    "name": "Luke Smith's Webpage",
    "desc": "Si no sabes quien es Luke Smith, no eres bienvenido aquí."
  },
  {
    "id": "05",
    "url": "https://www.tailsgetstrolled.org/",
    "img": "/static/buttons/tgt.gif",
    "name": "Tails Gets Trolled",
    "desc": "Una obra magna, cuyo valor es apreciado por unos pocos. desde que leí Tails Gets Trolled, soy más feliz conmigo mismo."
  },
  {
    "id": "06",
    "url": "https://fauux.neocities.org/",
    "img": "/static/buttons/fauux-btn.gif",
    "name": "Wired Sounds for Wired People",
    "desc": "¿Te gusta Lain? Pues disfruta de las melodías que tiene este sitio para ofrecer."
  },
  {
    "id": "07",
    "url": "https://nadeko.net/",
    "img": "/static/buttons/nadekodotnet.png",
    "name": "nadeko.net",
    "desc": "Fijxu (webmaster de nadeko.net) se dedica al self-hosting de varios servicios enfocados a la privacidad abiertos a todo el mundo."
  },
  {
    "id": "08",
    "url": "https://her.st",
    "name": "her.st",
    "desc": "Blog muy interesante acerca de minimalismo digital, selfhosting y eso..."
  },
  {
    "id": "09",
    "url": "https://lolcat.ca/",
    "name": "lolcat's website",
    "desc": "El mrk que creo 4get..."
  },
  {
    "id": "10",
    "url": "https://loquendotv.net/",
    "name": "Loquendo TV",
    "desc": "Instancia de PeerTube manejada por masones, usan loquendo para adoctrinar a los menos ilustrados."
  }
]
